mcp_server_twse/__init__.py
mcp_server_twse/py.typed
mcp_server_twse/server.py
mcp_server_twse/twse.py
mcp_server_twse-0.1.0.dist-info/METADATA
mcp_server_twse-0.1.0.dist-info/WHEEL
mcp_server_twse-0.1.0.dist-info/entry_points.txt
mcp_server_twse-0.1.0.dist-info/licenses/LICENSE
mcp_server_twse-0.1.0.dist-info/RECORD
